app/__init__.py
app/abstract.py
app/aws.py
app/core.py
app/main.py
SensorMiddleware-1.0.dist-info/AUTHORS
SensorMiddleware-1.0.dist-info/METADATA
SensorMiddleware-1.0.dist-info/WHEEL
SensorMiddleware-1.0.dist-info/entry_points.txt
SensorMiddleware-1.0.dist-info/top_level.txt
SensorMiddleware-1.0.dist-info/RECORD
