Metadata-Version: 2.1
Name: SensorMiddleware
Version: 1.0
Summary: Middleware para os Sensores EcoTrust
Author-email: pablo1920@protonmail.com
Classifier: Programming Language :: Python :: 3.7
Classifier: Operating System :: OS Independent
Requires-Python: >=3.7
License-File: AUTHORS
Requires-Dist: boto3
Requires-Dist: requests
